napari_save_transformed/__init__.py
napari_save_transformed/napari.yaml
napari_save_transformed-0.0.2.dist-info/METADATA
napari_save_transformed-0.0.2.dist-info/WHEEL
napari_save_transformed-0.0.2.dist-info/entry_points.txt
napari_save_transformed-0.0.2.dist-info/licenses/LICENSE.txt
napari_save_transformed-0.0.2.dist-info/RECORD
