Metadata-Version: 2.3
Name: napari-save-transformed
Version: 0.0.2
Summary: Napari plugin to save layers with their transforms applied.
Project-URL: Documentation, https://github.com/fmi-faim/napari-save-transformed#readme
Project-URL: Issues, https://github.com/fmi-faim/napari-save-transformed/issues
Project-URL: Source, https://github.com/fmi-faim/napari-save-transformed
Author-email: Jan Eglinger <jan.eglinger@fmi.ch>
License-Expression: BSD-3-Clause
License-File: LICENSE.txt
Classifier: Development Status :: 4 - Beta
Classifier: Framework :: napari
Classifier: Programming Language :: Python
Classifier: Programming Language :: Python :: 3.9
Classifier: Programming Language :: Python :: 3.10
Classifier: Programming Language :: Python :: 3.11
Classifier: Programming Language :: Python :: 3.12
Classifier: Programming Language :: Python :: Implementation :: CPython
Classifier: Programming Language :: Python :: Implementation :: PyPy
Requires-Python: >=3.9
Requires-Dist: napari
